rtl/moore_counter.v
module counter(
    input clk, rst, x,
    output reg y
);

reg[1:0] state, next_state;
parameter S0 = 2'b00, S1 = 2'b01, S2 = 2'b10, S3 = 2'b11;

always@(posedge clk, negedge rst)
begin
    if (!rst) state <= S0;
    else state <= next_state;
end

always@(state, x)
begin
    case(state)
        S0: if(x) next_state <= S1; else next_state <= S0;
        S1: if(x) next_state <= S2; else next_state <= S1;
        S2: if(x) next_state <= S3; else next_state <= S2;
        S3: if(x) next_state <= S0; else next_state <= S0;
    endcase
end

always@(state)
begin
    if(state == S3) y = 1'b1;
    else y = 0;
end

endmodule

tb/moore_counter_tb.v
module counter_tb;
reg clk, rst, x;
wire y;

counter DUT(.clk(clk), .rst(rst), .x(x), .y(y));

initial #80 $finish;
initial begin clk = 0; forever #5 clk = ~clk; end

initial fork
    rst = 0;
    #2 rst = 1;

    #3 x = 1;
    #7 x = 0;
    #20 x = 1;
    #29 x = 0;
    #35 x = 1;
join

    // Dump waveform
initial begin
    $dumpfile("counter_sim.vcd");
    $dumpvars(0, counter_tb);
    $dumpvars(1, DUT);
end
endmodule

sim/counter_sim.vcd
$date
	Fri Jul 11 04:07:46 2025
$end
$version
	Icarus Verilog
$end
$timescale
	1s
$end
$scope module counter_tb $end
$var wire 1 ! y $end
$var reg 1 " clk $end
$var reg 1 # rst $end
$var reg 1 $ x $end
$scope module DUT $end
$var wire 1 " clk $end
$var wire 1 # rst $end
$var wire 1 $ x $end
$var parameter 2 % S0 $end
$var parameter 2 & S1 $end
$var parameter 2 ' S2 $end
$var parameter 2 ( S3 $end
$var reg 2 ) next_state [1:0] $end
$var reg 2 * state [1:0] $end
$var reg 1 ! y $end
$upscope $end
$upscope $end
$scope module counter_tb $end
$scope module DUT $end
$upscope $end
$upscope $end
$enddefinitions $end
$comment Show the parameter values. $end
$dumpall
b11 (
b10 '
b1 &
b0 %
$end
#0
$dumpvars
b0 *
b0 )
x$
0#
0"
0!
$end
#2
1#
#3
b1 )
1$
#5
b10 )
b1 *
1"
#7
b1 )
0$
#10
0"
#15
1"
#20
b10 )
0"
1$
#25
b11 )
b10 *
1"
#29
b10 )
0$
#30
0"
#35
b11 )
1"
1$
#40
0"
#45
b0 )
1!
b11 *
1"
#50
0"
#55
b1 )
0!
b0 *
1"
#60
0"
#65
b10 )
b1 *
1"
#70
0"
#75
b11 )
b10 *
1"
