rtl/pwdProtect.v
module pwd_unlock(
    input clk, rst,
    input [1:0] key,
    output wire unlock
);

reg[2:0] counter;
parameter K1 = 2'b10, 
          K2 = 2'b01, 
          K3 = 2'b10, 
          K4 = 2'b11; 

always@(posedge clk, negedge rst)
begin
    if (!rst) begin
        counter <= 0;
    end else 
            begin
                case(counter)
                    0: if (key == K1) counter <= 1; else counter <= 0;
                    1: if (key == K2) counter <= 2; else counter <= 0;
                    2: if (key == K3) counter <= 3; else counter <= 0;
                    3: if (key == K4) counter <= 4; else counter <= 0;
                endcase
            end
end

assign unlock = (counter == 4) ? 1 : 0;
endmodule

tb/pwdProtect_tb.v
module pwd_unlock_tb;
reg clk, rst;
reg[1:0] key;
wire unlock;

pwd_unlock DUT(.clk(clk), .rst(rst), .key(key), .unlock(unlock));

initial #200 $finish;
initial begin 
    clk = 0;
    forever #5 clk = ~clk;
end

initial fork
    rst = 0;
    key = 2'b00;
    #2 rst = 1; 

    #12 key = 2'b10; 
    #22 key = 2'b01; 
    #32 key = 2'b10; 
    #42 key = 2'b11; 
join

initial begin
    $dumpfile("pwd_sim.vcd");
    $dumpvars(0, pwd_unlock_tb);
    $dumpvars(0, DUT);
end
endmodule

sim/pwd_sim.vcd
$date
	Sun Jul 13 01:39:49 2025
$end
$version
	Icarus Verilog
$end
$timescale
	1s
$end
$scope module pwd_unlock_tb $end
$var wire 1 ! unlock $end
$var reg 1 " clk $end
$var reg 2 # key [1:0] $end
$var reg 1 $ rst $end
$scope module DUT $end
$var wire 1 " clk $end
$var wire 2 % key [1:0] $end
$var wire 1 $ rst $end
$var wire 1 ! unlock $end
$var parameter 2 & K1 $end
$var parameter 2 ' K2 $end
$var parameter 2 ( K3 $end
$var parameter 2 ) K4 $end
$var reg 3 * counter [2:0] $end
$upscope $end
$upscope $end
$scope module pwd_unlock_tb $end
$scope module DUT $end
$upscope $end
$upscope $end
$enddefinitions $end
$comment Show the parameter values. $end
$dumpall
b11 )
b10 (
b1 '
b10 &
$end
#0
$dumpvars
b0 *
b0 %
0$
b0 #
0"
0!
$end
#2
1$
#5
1"
#10
0"
#12
b10 #
b10 %
#15
b1 *
1"
#20
0"
#22
b1 #
b1 %
#25
b10 *
1"
#30
0"
#32
b10 #
b10 %
#35
b11 *
1"
#40
0"
#42
b11 #
b11 %
#45
1!
b100 *
1"
