rtl/seq_det.v
module mealy_mac(
    input clk, rst, x,
    output reg y
);

parameter S0 = 2'b00, S1 = 2'b01, S2 = 2'b10, S3 = 2'b11;
reg[1:0] state, next_state;

always@(posedge clk, negedge rst)
begin
    if (!rst) state <= S0;
    else state <= next_state;
end

always@(state, x)
begin
    case(state)
        S0: if(x) next_state <= S1; else next_state <= S0;
        S1: if(x) next_state <= S3; else next_state <= S0;
        S2: if(!x) next_state <= S0; else next_state <= S2;
        S3: if(x) next_state <= S2; else next_state <= S0;
    endcase
end

always@(state, x)
begin
    case(state)
        S0: y = 0;
        S1, S2, S3: y = !x;
    endcase
end
endmodule

tb/seq_det_tb.v
module mealy_mac_tb;
reg clk, rst, x;
wire y;

mealy_mac DUT(.clk(clk), .rst(rst), .x(x), .y(y));

initial #200 $finish;
initial begin clk = 0; forever #5 clk = ~clk; end

initial fork
    rst = 0;
    #2 rst = 1;
    #87 rst = 0;
    #89 rst = 1;

    #10 x = 1;
    #30 x = 0;
    #40 x = 1;
    #50 x = 0;
    #52 x = 1;
    #54 x = 0;
    #80 x = 1;
    #100 x = 0;
    #120 x = 1;
join

    // Dump waveform
initial begin
    $dumpfile("seq_det_sim.vcd");
    $dumpvars(1, mealy_mac_tb);
end
endmodule

sim/seq_det_sim.vcd
$date
	Thu Jul 10 00:27:39 2025
$end
$version
	Icarus Verilog
$end
$timescale
	1s
$end
$scope module mealy_mac_tb $end
$var wire 1 ! y $end
$var reg 1 " clk $end
$var reg 1 # rst $end
$var reg 1 $ x $end
$upscope $end
$enddefinitions $end
$comment Show the parameter values. $end
$dumpall
$end
#0
$dumpvars
x$
0#
0"
0!
$end
#2
1#
#5
1"
#10
0"
1$
#15
1"
#20
0"
#25
1"
#30
1!
0"
0$
#35
0!
1"
#40
0"
1$
#45
1"
#50
1!
0"
0$
#52
0!
1$
#54
1!
0$
#55
0!
1"
#60
0"
#65
1"
#70
0"
#75
1"
#80
0"
1$
#85
1"
#87
0#
#89
1#
#90
0"
#95
1"
#100
1!
0"
0$
#105
0!
1"
#110
0"
#115
1"
#120
0"
1$
