rtl/serial_adder.v
module FA(
    input A, B, Cin,
    output sum, Cout
);
assign sum = (A ^ B) ^ Cin;
assign Cout = (A & B) | (B & Cin) | (A & Cin);
endmodule

module dff(
    input clk, rst, D,
    output reg Q
);
always@(posedge clk, negedge rst) begin
    if (!rst) Q <= 1'b0;
    else Q <= D;
end
endmodule

module reg4(
    input clk, rst, sIn,
    output sOut
);
wire t1, t2, t3;
dff D1(clk, rst, sIn, t1);
dff D2(clk, rst, t1, t2);
dff D3(clk, rst, t2, t3);
dff D4(clk, rst, t3, sOut);
endmodule

module serAdder(
    input clk, rst, load, A, B,
    output S
);
wire t1, t2, S1, C1, C2;

reg4 RA(clk, rst, A, t1); //input reg A
reg4 RB(clk, rst, B, t2); //input reg B

//load blocks the input to the FA by setting it to 0
FA FA1(t1 & load, t2 & load, C1, S1, C2); //full adder
dff FF1(clk, rst, C2, C1); //dff to store carry

reg4 RC(clk, rst, S1, S); //sum register
endmodule

tb/serial_adder_tb.v
module serAdder_tb;
reg clk, rst, load, A, B;
wire S;

serAdder DUT(clk, rst, load, A, B, S);

initial #90 $finish;
initial begin
    clk = 0;
    forever #5 clk = ~clk;
end

initial begin
    $dumpfile("serAdder_sim.vcd");
    $dumpvars(0, serAdder_tb);

    $display("clk | load | s1 | s2 | s3 | s4");
    $monitor("%b | %b | %b | %b | %b | %b", clk, load, DUT.RC.D1.Q, DUT.RC.D2.Q, DUT.RC.D3.Q, DUT.RC.D4.Q);

    rst = 0;
    load = 0;
    A = 0; B = 0;

    #5 rst = 1;

    #10 A = 0; B = 1;
    #10 A = 1; B = 1;
    #10 A = 0; B = 1;
    #10 A = 1; B = 0;

    #3 load = 1;
    #40 load = 0;
end
endmodule

sim/serAdder_sim.vcd
$date
	Sat Aug  9 09:41:54 2025
$end
$version
	Icarus Verilog
$end
$timescale
	1s
$end
$scope module serAdder_tb $end
$var wire 1 ! S $end
$var reg 1 " A $end
$var reg 1 # B $end
$var reg 1 $ clk $end
$var reg 1 % load $end
$var reg 1 & rst $end
$scope module DUT $end
$var wire 1 " A $end
$var wire 1 # B $end
$var wire 1 $ clk $end
$var wire 1 % load $end
$var wire 1 & rst $end
$var wire 1 ' t2 $end
$var wire 1 ( t1 $end
$var wire 1 ) S1 $end
$var wire 1 ! S $end
$var wire 1 * C2 $end
$var wire 1 + C1 $end
$scope module FA1 $end
$var wire 1 , A $end
$var wire 1 - B $end
$var wire 1 * Cout $end
$var wire 1 ) sum $end
$var wire 1 + Cin $end
$upscope $end
$scope module FF1 $end
$var wire 1 * D $end
$var wire 1 $ clk $end
$var wire 1 & rst $end
$var reg 1 + Q $end
$upscope $end
$scope module RA $end
$var wire 1 $ clk $end
$var wire 1 & rst $end
$var wire 1 " sIn $end
$var wire 1 . t3 $end
$var wire 1 / t2 $end
$var wire 1 0 t1 $end
$var wire 1 ( sOut $end
$scope module D1 $end
$var wire 1 " D $end
$var wire 1 $ clk $end
$var wire 1 & rst $end
$var reg 1 0 Q $end
$upscope $end
$scope module D2 $end
$var wire 1 0 D $end
$var wire 1 $ clk $end
$var wire 1 & rst $end
$var reg 1 / Q $end
$upscope $end
$scope module D3 $end
$var wire 1 / D $end
$var wire 1 $ clk $end
$var wire 1 & rst $end
$var reg 1 . Q $end
$upscope $end
$scope module D4 $end
$var wire 1 . D $end
$var wire 1 $ clk $end
$var wire 1 & rst $end
$var reg 1 ( Q $end
$upscope $end
$upscope $end
$scope module RB $end
$var wire 1 $ clk $end
$var wire 1 & rst $end
$var wire 1 # sIn $end
$var wire 1 1 t3 $end
$var wire 1 2 t2 $end
$var wire 1 3 t1 $end
$var wire 1 ' sOut $end
$scope module D1 $end
$var wire 1 # D $end
$var wire 1 $ clk $end
$var wire 1 & rst $end
$var reg 1 3 Q $end
$upscope $end
$scope module D2 $end
$var wire 1 3 D $end
$var wire 1 $ clk $end
$var wire 1 & rst $end
$var reg 1 2 Q $end
$upscope $end
$scope module D3 $end
$var wire 1 2 D $end
$var wire 1 $ clk $end
$var wire 1 & rst $end
$var reg 1 1 Q $end
$upscope $end
$scope module D4 $end
$var wire 1 1 D $end
$var wire 1 $ clk $end
$var wire 1 & rst $end
$var reg 1 ' Q $end
$upscope $end
$upscope $end
$scope module RC $end
$var wire 1 $ clk $end
$var wire 1 & rst $end
$var wire 1 ) sIn $end
$var wire 1 4 t3 $end
$var wire 1 5 t2 $end
$var wire 1 6 t1 $end
$var wire 1 ! sOut $end
$scope module D1 $end
$var wire 1 ) D $end
$var wire 1 $ clk $end
$var wire 1 & rst $end
$var reg 1 6 Q $end
$upscope $end
$scope module D2 $end
$var wire 1 6 D $end
$var wire 1 $ clk $end
$var wire 1 & rst $end
$var reg 1 5 Q $end
$upscope $end
$scope module D3 $end
$var wire 1 5 D $end
$var wire 1 $ clk $end
$var wire 1 & rst $end
$var reg 1 4 Q $end
$upscope $end
$scope module D4 $end
$var wire 1 4 D $end
$var wire 1 $ clk $end
$var wire 1 & rst $end
$var reg 1 ! Q $end
$upscope $end
$upscope $end
$upscope $end
$upscope $end
$enddefinitions $end
$comment Show the parameter values. $end
$dumpall
$end
#0
$dumpvars
06
05
04
03
02
01
00
0/
0.
0-
0,
0+
0*
0)
0(
0'
0&
0%
0$
0#
0"
0!
$end
#5
1&
1$
#10
0$
#15
13
1$
1#
#20
0$
#25
12
10
1$
1"
#30
0$
#35
00
1/
11
1$
0"
#40
0$
#45
1'
03
1.
0/
10
1$
0#
1"
#48
1)
1-
1%
#50
0$
#55
1*
0)
1,
1/
0.
1(
02
16
1$
#60
0$
#65
0)
0,
15
06
1+
01
0(
1.
1$
#70
0$
#75
1,
0-
1(
0'
05
14
1$
#80
0$
#85
1!
04
1$
#88
1)
0*
0,
0%
