rtl/serial_adder.v
module FA(
    input A, B, Cin,
    output sum, Cout
);
assign sum = (A ^ B) ^ Cin;
assign Cout = (A & B) | (B & Cin) | (A & Cin);
endmodule

module mux21(
    input A, B, S,
    output Y
);
assign Y = ((~S) & A) | (S & B);
endmodule

module dff(
    input clk, rst, D,
    output reg Q
);
always@(posedge clk, negedge rst) begin
    if (!rst) Q <= 1'b0;
    else Q <= D;
end
endmodule

module reg4(
    input clk, rst, sIn, load,
    output sOut
);
wire t1, t2, t3;
wire in1, in2, in3, in4;

mux21 M1(t1, sIn, load, in1);
dff D1(clk, rst, in1, t1);

mux21 M2(t2, t1, load, in2);
dff D2(clk, rst, in2, t2);

mux21 M3(t3, t2, load, in3);
dff D3(clk, rst, in3, t3);

mux21 M4(sOut, t3, load, in4);
dff D4(clk, rst, in4, sOut);
endmodule

module serAdder(
    input clk, rst, load, A, B,
    output S
);
wire t1, t2, S1, C1, C2;

reg4 RA(clk, rst, A, 1'b1, t1); //input reg A
reg4 RB(clk, rst, B, 1'b1, t2); //input reg B

//load blocks the input to the FA by setting it to 0
FA FA1(t1 & load, t2 & load, C1, S1, C2); //full adder
dff FF1(clk, rst, C2, C1); //dff to store carry

reg4 RC(clk, rst, S1, load, S); //sum register
endmodule

tb/serial_adder_tb.v
module serAdder_tb;
reg clk, rst, load, A, B;
wire S;

serAdder DUT(clk, rst, load, A, B, S);

initial #100 $finish;
initial begin
    clk = 0;
    forever #5 clk = ~clk;
end

initial begin
    $dumpfile("serAdder_sim.vcd");
    $dumpvars(0, serAdder_tb);

    $display("clk | load | s1 | s2 | s3 | s4");
    $monitor("%b | %b | %b | %b | %b | %b", clk, load, DUT.RC.D1.Q, DUT.RC.D2.Q, DUT.RC.D3.Q, DUT.RC.D4.Q);

    rst = 0;
    load = 0;
    A = 0; B = 0;

    #5 rst = 1;

    #10 A = 0; B = 1;
    #10 A = 1; B = 1;
    #10 A = 0; B = 1;
    #10 A = 1; B = 0;

    #3 load = 1;
    #50 load = 0;
end
endmodule

sim/serAdder_sim.vcd
$date
	Sat Aug  9 10:13:39 2025
$end
$version
	Icarus Verilog
$end
$timescale
	1s
$end
$scope module serAdder_tb $end
$var wire 1 ! S $end
$var reg 1 " A $end
$var reg 1 # B $end
$var reg 1 $ clk $end
$var reg 1 % load $end
$var reg 1 & rst $end
$scope module DUT $end
$var wire 1 " A $end
$var wire 1 # B $end
$var wire 1 $ clk $end
$var wire 1 % load $end
$var wire 1 & rst $end
$var wire 1 ' t2 $end
$var wire 1 ( t1 $end
$var wire 1 ) S1 $end
$var wire 1 ! S $end
$var wire 1 * C2 $end
$var wire 1 + C1 $end
$scope module FA1 $end
$var wire 1 , A $end
$var wire 1 - B $end
$var wire 1 * Cout $end
$var wire 1 ) sum $end
$var wire 1 + Cin $end
$upscope $end
$scope module FF1 $end
$var wire 1 * D $end
$var wire 1 $ clk $end
$var wire 1 & rst $end
$var reg 1 + Q $end
$upscope $end
$scope module RA $end
$var wire 1 $ clk $end
$var wire 1 . load $end
$var wire 1 & rst $end
$var wire 1 " sIn $end
$var wire 1 / t3 $end
$var wire 1 0 t2 $end
$var wire 1 1 t1 $end
$var wire 1 ( sOut $end
$var wire 1 2 in4 $end
$var wire 1 3 in3 $end
$var wire 1 4 in2 $end
$var wire 1 5 in1 $end
$scope module D1 $end
$var wire 1 $ clk $end
$var wire 1 & rst $end
$var wire 1 5 D $end
$var reg 1 1 Q $end
$upscope $end
$scope module D2 $end
$var wire 1 $ clk $end
$var wire 1 & rst $end
$var wire 1 4 D $end
$var reg 1 0 Q $end
$upscope $end
$scope module D3 $end
$var wire 1 $ clk $end
$var wire 1 & rst $end
$var wire 1 3 D $end
$var reg 1 / Q $end
$upscope $end
$scope module D4 $end
$var wire 1 $ clk $end
$var wire 1 & rst $end
$var wire 1 2 D $end
$var reg 1 ( Q $end
$upscope $end
$scope module M1 $end
$var wire 1 1 A $end
$var wire 1 " B $end
$var wire 1 . S $end
$var wire 1 5 Y $end
$upscope $end
$scope module M2 $end
$var wire 1 0 A $end
$var wire 1 1 B $end
$var wire 1 . S $end
$var wire 1 4 Y $end
$upscope $end
$scope module M3 $end
$var wire 1 / A $end
$var wire 1 0 B $end
$var wire 1 . S $end
$var wire 1 3 Y $end
$upscope $end
$scope module M4 $end
$var wire 1 ( A $end
$var wire 1 / B $end
$var wire 1 . S $end
$var wire 1 2 Y $end
$upscope $end
$upscope $end
$scope module RB $end
$var wire 1 $ clk $end
$var wire 1 6 load $end
$var wire 1 & rst $end
$var wire 1 # sIn $end
$var wire 1 7 t3 $end
$var wire 1 8 t2 $end
$var wire 1 9 t1 $end
$var wire 1 ' sOut $end
$var wire 1 : in4 $end
$var wire 1 ; in3 $end
$var wire 1 < in2 $end
$var wire 1 = in1 $end
$scope module D1 $end
$var wire 1 $ clk $end
$var wire 1 & rst $end
$var wire 1 = D $end
$var reg 1 9 Q $end
$upscope $end
$scope module D2 $end
$var wire 1 $ clk $end
$var wire 1 & rst $end
$var wire 1 < D $end
$var reg 1 8 Q $end
$upscope $end
$scope module D3 $end
$var wire 1 $ clk $end
$var wire 1 & rst $end
$var wire 1 ; D $end
$var reg 1 7 Q $end
$upscope $end
$scope module D4 $end
$var wire 1 $ clk $end
$var wire 1 & rst $end
$var wire 1 : D $end
$var reg 1 ' Q $end
$upscope $end
$scope module M1 $end
$var wire 1 9 A $end
$var wire 1 # B $end
$var wire 1 6 S $end
$var wire 1 = Y $end
$upscope $end
$scope module M2 $end
$var wire 1 8 A $end
$var wire 1 9 B $end
$var wire 1 6 S $end
$var wire 1 < Y $end
$upscope $end
$scope module M3 $end
$var wire 1 7 A $end
$var wire 1 8 B $end
$var wire 1 6 S $end
$var wire 1 ; Y $end
$upscope $end
$scope module M4 $end
$var wire 1 ' A $end
$var wire 1 7 B $end
$var wire 1 6 S $end
$var wire 1 : Y $end
$upscope $end
$upscope $end
$scope module RC $end
$var wire 1 $ clk $end
$var wire 1 % load $end
$var wire 1 & rst $end
$var wire 1 ) sIn $end
$var wire 1 > t3 $end
$var wire 1 ? t2 $end
$var wire 1 @ t1 $end
$var wire 1 ! sOut $end
$var wire 1 A in4 $end
$var wire 1 B in3 $end
$var wire 1 C in2 $end
$var wire 1 D in1 $end
$scope module D1 $end
$var wire 1 $ clk $end
$var wire 1 & rst $end
$var wire 1 D D $end
$var reg 1 @ Q $end
$upscope $end
$scope module D2 $end
$var wire 1 $ clk $end
$var wire 1 & rst $end
$var wire 1 C D $end
$var reg 1 ? Q $end
$upscope $end
$scope module D3 $end
$var wire 1 $ clk $end
$var wire 1 & rst $end
$var wire 1 B D $end
$var reg 1 > Q $end
$upscope $end
$scope module D4 $end
$var wire 1 $ clk $end
$var wire 1 & rst $end
$var wire 1 A D $end
$var reg 1 ! Q $end
$upscope $end
$scope module M1 $end
$var wire 1 @ A $end
$var wire 1 ) B $end
$var wire 1 % S $end
$var wire 1 D Y $end
$upscope $end
$scope module M2 $end
$var wire 1 ? A $end
$var wire 1 @ B $end
$var wire 1 % S $end
$var wire 1 C Y $end
$upscope $end
$scope module M3 $end
$var wire 1 > A $end
$var wire 1 ? B $end
$var wire 1 % S $end
$var wire 1 B Y $end
$upscope $end
$scope module M4 $end
$var wire 1 ! A $end
$var wire 1 > B $end
$var wire 1 % S $end
$var wire 1 A Y $end
$upscope $end
$upscope $end
$upscope $end
$upscope $end
$enddefinitions $end
$comment Show the parameter values. $end
$dumpall
$end
#0
$dumpvars
0D
0C
0B
0A
0@
0?
0>
0=
0<
0;
0:
09
08
07
16
05
04
03
02
01
00
0/
1.
0-
0,
0+
0*
0)
0(
0'
0&
0%
0$
0#
0"
0!
$end
#5
1&
1$
#10
0$
#15
1=
1$
1#
#20
0$
#25
1<
19
15
1$
1"
#30
0$
#35
14
1;
11
18
05
1$
0"
#40
0$
#45
1:
13
04
17
10
01
0=
15
1$
0#
1"
#48
1%
#50
0$
#55
1D
1)
14
03
12
0<
1-
11
00
1/
09
1'
1$
#60
0$
#65
0D
1*
0)
1C
0;
02
13
1,
1@
08
1(
0/
10
1$
#70
0$
#75
0D
12
0:
0C
1B
0,
0)
1/
0(
07
1+
0@
1?
1$
#80
0$
#85
1A
0B
0-
1,
1>
0?
0'
1(
1$
#90
0$
#95
0A
0>
1!
1$
#98
1)
0*
1A
0,
0%
