rtl/problems/sol_546.v
module solution(
    input clk, rst, x_in,
    output y_out
);
parameter IDLE = 3'b000, 
          ACTIVE1= 3'b001, 
          ACTIVE2= 3'b010, 
          ACTIVE3= 3'b011, 
          LOW1= 3'b100, 
          LOW2= 3'b101;
reg [3:0] state, next_state;
reg x_state;
wire x_rise;

always@(posedge clk, negedge rst) begin
    if (!rst) state <= IDLE;
    else begin
        if (state >= ACTIVE1 && state < LOW2) state <= state + 1;
        else state <= next_state;
    end

    x_state <= x_in;
end

always@(state, x_rise) begin
    if (state == IDLE && x_rise == 1) 
        next_state = ACTIVE1;
    else if (state >= ACTIVE1 && state <= LOW2) begin
        if (state == ACTIVE3)
            next_state = LOW1;
        else if (state == LOW2)
            next_state = IDLE;
    end
    else next_state = IDLE;
end

assign y_out = ~(state == IDLE || state == LOW1 || state == LOW2);
assign x_rise = (~x_state & x_in);
endmodule

tb/problems/sol_546_tb.v
module solution_tb;
reg clk, rst, x_in;
wire y_out;

solution DUT(clk, rst, x_in, y_out);

initial #200 $finish;
initial begin
	clk = 0;
	forever #5 clk = ~clk;
end

initial begin
	$dumpfile("sol_sim.vcd");
	$dumpvars(0, solution_tb);

	rst = 0;
	x_in = 0;
	
	#2 rst = 1;
	#8 x_in = 1;
	#23 x_in = 0;
	#37 x_in = 1;
end
endmodule

sim/sol_sim.vcd
$date
	Thu Jul 24 13:58:18 2025
$end
$version
	Icarus Verilog
$end
$timescale
	1s
$end
$scope module solution_tb $end
$var wire 1 ! y_out $end
$var reg 1 " clk $end
$var reg 1 # rst $end
$var reg 1 $ x_in $end
$scope module DUT $end
$var wire 1 " clk $end
$var wire 1 # rst $end
$var wire 1 $ x_in $end
$var wire 1 % x_rise $end
$var wire 1 ! y_out $end
$var parameter 3 & ACTIVE1 $end
$var parameter 3 ' ACTIVE2 $end
$var parameter 3 ( ACTIVE3 $end
$var parameter 3 ) IDLE $end
$var parameter 3 * LOW1 $end
$var parameter 3 + LOW2 $end
$var reg 4 , next_state [3:0] $end
$var reg 4 - state [3:0] $end
$var reg 1 . x_state $end
$upscope $end
$upscope $end
$enddefinitions $end
$comment Show the parameter values. $end
$dumpall
b101 +
b100 *
b0 )
b11 (
b10 '
b1 &
$end
#0
$dumpvars
0.
b0 -
b0 ,
0%
0$
0#
0"
0!
$end
#2
1#
#5
1"
#10
b1 ,
1%
0"
1$
#15
1!
0%
1.
b1 -
1"
#20
0"
#25
b10 -
1"
#30
0"
#33
0$
#35
b100 ,
0.
b11 -
1"
#40
0"
#45
0!
b100 -
1"
#50
0"
#55
b0 ,
b101 -
1"
#60
0"
#65
0!
b0 -
1"
#70
b1 ,
1%
0"
1$
#75
1!
0%
1.
b1 -
1"
#80
0"
#85
b10 -
1"
#90
0"
#95
b100 ,
b11 -
1"
#100
0"
#105
0!
b100 -
1"
#110
0"
#115
b0 ,
b101 -
1"
#120
0"
#125
0!
b0 -
1"
